motives/__init__.py
motives/core/__init__.py
motives/core/lambda_ring_context.py
motives/core/lambda_ring_expr.py
motives/core/operand/__init__.py
motives/core/operand/object_1_dim.py
motives/core/operand/operand.py
motives/core/operand/rational_operand.py
motives/core/operator/__init__.py
motives/core/operator/nary_operator.py
motives/core/operator/pow_operator.py
motives/core/operator/ring_operator.py
motives/free.py
motives/grothendieck_motives/__init__.py
"motives/grothendieck_motives/curves/__init__,py"
motives/grothendieck_motives/curves/curve.py
motives/grothendieck_motives/curves/curvechow.py
motives/grothendieck_motives/curves/jacobian.py
motives/grothendieck_motives/curves/piccard.py
motives/grothendieck_motives/groups/__init__.py
motives/grothendieck_motives/groups/general_groups.py
motives/grothendieck_motives/groups/gl.py
motives/grothendieck_motives/groups/o.py
motives/grothendieck_motives/groups/pgl.py
motives/grothendieck_motives/groups/psl.py
motives/grothendieck_motives/groups/pso.py
motives/grothendieck_motives/groups/semisimple_g.py
motives/grothendieck_motives/groups/sl.py
motives/grothendieck_motives/groups/so.py
motives/grothendieck_motives/groups/sp.py
motives/grothendieck_motives/lefschetz.py
motives/grothendieck_motives/moduli/__init__.py
motives/grothendieck_motives/moduli/scheme/__init__.py
motives/grothendieck_motives/moduli/scheme/bundle_moduli.py
motives/grothendieck_motives/moduli/scheme/twisted_higgs_moduli.py
motives/grothendieck_motives/moduli/scheme/twisted_higgs_moduli_adhm.py
motives/grothendieck_motives/moduli/scheme/twisted_higgs_moduli_bb.py
motives/grothendieck_motives/moduli/scheme/vector_bundle_moduli.py
motives/grothendieck_motives/moduli/scheme/vhs.py
motives/grothendieck_motives/moduli/stack/__init__.py
motives/grothendieck_motives/moduli/stack/bundet.py
motives/grothendieck_motives/moduli/stack/bung.py
motives/grothendieck_motives/motive.py
motives/grothendieck_motives/point.py
motives/grothendieck_motives/proj.py
motives-0.3.3.dist-info/LICENSE
motives-0.3.3.dist-info/METADATA
motives-0.3.3.dist-info/WHEEL
motives-0.3.3.dist-info/RECORD
