Metadata-Version: 2.1
Name: motives
Version: 0.3.3
Summary: Software package that allows efficient manipulation and comparison of Grothendieck motives in lambda-rings.
Author: Daniel Sánchez Sánchez
Author-email: danielsanchezs1905@gmail.com
Requires-Python: >=3.10.6,<4.0.0
Classifier: Programming Language :: Python :: 3
Classifier: Programming Language :: Python :: 3.11
Classifier: Programming Language :: Python :: 3.12
Requires-Dist: sympy (>=1.12,<2.0)
Requires-Dist: tqdm (==4.66.1)
Requires-Dist: typeguard (==4.3.0)
